grpc_helper_api/__init__.py
grpc_helper_api/common.proto
grpc_helper_api/common_pb2.py
grpc_helper_api/common_pb2_grpc.py
grpc_helper_api/config.proto
grpc_helper_api/config_pb2.py
grpc_helper_api/config_pb2_grpc.py
grpc_helper_api/events.proto
grpc_helper_api/events_pb2.py
grpc_helper_api/events_pb2_grpc.py
grpc_helper_api/logger.proto
grpc_helper_api/logger_pb2.py
grpc_helper_api/logger_pb2_grpc.py
grpc_helper_api/server.proto
grpc_helper_api/server_pb2.py
grpc_helper_api/server_pb2_grpc.py
grpc_helper_api-2.0.4.dist-info/LICENSE
grpc_helper_api-2.0.4.dist-info/METADATA
grpc_helper_api-2.0.4.dist-info/WHEEL
grpc_helper_api-2.0.4.dist-info/top_level.txt
grpc_helper_api-2.0.4.dist-info/RECORD
