Metadata-Version: 2.1
Name: grpc-helper-api
Version: 2.0.4
Summary: API module for grpc_helper
Home-page: https://github.com/dynod/grpc-helper-api
Author: The dynod project
Maintainer: The dynod project
License: Mozilla Public License Version 2.0
Platform: UNKNOWN
Classifier: Programming Language :: Python :: 3.8
Classifier: Programming Language :: Python :: 3.9
Classifier: Programming Language :: Python :: 3.10
Classifier: Programming Language :: Python :: 3.11
Requires-Dist: grpcio
Requires-Dist: protobuf
